README.md
package_info.json
setup.py
th2_grpc_act_ssh/__init__.py
th2_grpc_act_ssh/act_ssh.proto
th2_grpc_act_ssh/act_ssh_pb2.py
th2_grpc_act_ssh/act_ssh_pb2.pyi
th2_grpc_act_ssh/act_ssh_pb2_grpc.py
th2_grpc_act_ssh/act_ssh_service.py
th2_grpc_act_ssh/py.typed
th2_grpc_act_ssh.egg-info/PKG-INFO
th2_grpc_act_ssh.egg-info/SOURCES.txt
th2_grpc_act_ssh.egg-info/dependency_links.txt
th2_grpc_act_ssh.egg-info/requires.txt
th2_grpc_act_ssh.egg-info/top_level.txt