Metadata-Version: 2.1
Name: th2-grpc-act-ssh
Version: 1.1.0.dev4144944287
Summary: th2_grpc_act_ssh
Home-page: https://github.com/th2-net/th2-grpc-act-ssh
Author: TH2-devs
Author-email: th2-devs@exactprosystems.com
License: Apache License 2.0
Platform: UNKNOWN
Requires-Python: >=3.7
